tutorials/__init__.py
tutorials/cnn_mnist.py
fiwtools-0.1.0.dist-info/LICENSE
fiwtools-0.1.0.dist-info/METADATA
fiwtools-0.1.0.dist-info/WHEEL
fiwtools-0.1.0.dist-info/top_level.txt
fiwtools-0.1.0.dist-info/RECORD
