Metadata-Version: 2.1
Name: fiwtools
Version: 0.1.0
Summary: Families In the WIld: A Kinship Recogntion Toolbox.
Home-page: https://github.com/visionjo/FIW_KRT
Author: Joseph Robinson
Author-email: robinson.jo@husky.neu.edu
License: MIT License
